LICENSE
MANIFEST.in
README
setup.cfg
setup.py
locallocustio.egg-info/PKG-INFO
locallocustio.egg-info/SOURCES.txt
locallocustio.egg-info/dependency_links.txt
locallocustio.egg-info/entry_points.txt
locallocustio.egg-info/not-zip-safe
locallocustio.egg-info/requires.txt
locallocustio.egg-info/top_level.txt
locust/__init__.py
locust/__main__.py
locust/argument_parser.py
locust/clients.py
locust/core.py
locust/env.py
locust/event.py
locust/exception.py
locust/inspectlocust.py
locust/log.py
locust/main.py
locust/runners.py
locust/sequential_taskset.py
locust/stats.py
locust/wait_time.py
locust/web.py
locust/contrib/__init__.py
locust/contrib/fasthttp.py
locust/rpc/__init__.py
locust/rpc/protocol.py
locust/rpc/zmqrpc.py
locust/static/chart.js
locust/static/echarts.common.min.js
locust/static/jquery-1.11.3.min.js
locust/static/jquery.jqote2.min.js
locust/static/jquery.tools.min.js
locust/static/locust.js
locust/static/style.css
locust/static/vintage.js
locust/static/img/favicon.ico
locust/static/img/logo.png
locust/static/img/top_bg.png
locust/templates/index.html
locust/test/__init__.py
locust/test/mock_locustfile.py
locust/test/mock_logging.py
locust/test/test_client.py
locust/test/test_fasthttp.py
locust/test/test_locust_class.py
locust/test/test_main.py
locust/test/test_old_wait_api.py
locust/test/test_parser.py
locust/test/test_runners.py
locust/test/test_sequential_taskset.py
locust/test/test_stats.py
locust/test/test_taskratio.py
locust/test/test_util.py
locust/test/test_wait_time.py
locust/test/test_web.py
locust/test/test_zmqrpc.py
locust/test/testcases.py
locust/util/__init__.py
locust/util/cache.py
locust/util/deprecation.py
locust/util/exception_handler.py
locust/util/rounding.py
locust/util/timespan.py