Metadata-Version: 1.1
Name: locallocustio
Version: 1.0
Summary: Website load testing framework
Home-page: https://locust.io/
Author: Jonatan Heyman, Carl Bystrom, Joakim Hamrén, Hugo Heyman
Author-email: yunfan.zhang@shopee.com
License: MIT
Platform: UNKNOWN
Classifier: Topic :: Software Development :: Testing :: Traffic Generation
Classifier: Development Status :: 5 - Production/Stable
Classifier: License :: OSI Approved :: MIT License
Classifier: Operating System :: OS Independent
Classifier: Programming Language :: Python
Classifier: Programming Language :: Python :: 3
Classifier: Programming Language :: Python :: 3.6
Classifier: Programming Language :: Python :: 3.7
Classifier: Programming Language :: Python :: 3.8
Classifier: Intended Audience :: Developers
Classifier: Intended Audience :: System Administrators
